generator_zadan/__init__.py
generator_zadan/generator_zadan.py
generator_zadan/generatory/__init__.py
generator_zadan/generatory/calki_nieoznaczone.py
generator_zadan/generatory/calki_oznaczone.py
generator_zadan/generatory/calki_podwojne.py
generator_zadan/generatory/calki_podwojne_bez_wykresow.py
generator_zadan/generatory/generuj_zestaw.py
generator_zadan/generatory/geometria_analityczna.py
generator_zadan/generatory/gotowe/calka_nieoznaczona_typ_3.pickle
generator_zadan/generatory/gotowe/calka_oznaczona_typ_3.pickle
generator_zadan/generatory/gotowe/calka_oznaczona_typ_4.pickle
generator_zadan/generatory/gotowe/dzialania_zespolone.pickle
generator_zadan/generatory/gotowe/macierz_odwrotna_parametr_wymiar_3.pickle
generator_zadan/generatory/gotowe/macierz_odwrotna_parametr_wymiar_4.pickle
generator_zadan/generatory/gotowe/macierz_wyznacznik_parametr_wymiar_4.pickle
generator_zadan/generatory/gotowe/monotonicznosc_typ_2.pickle
generator_zadan/generatory/gotowe/monotonicznosc_typ_3.pickle
generator_zadan/generatory/gotowe/odleglosc_prostych_skosnych.pickle
generator_zadan/generatory/gotowe/uklad_Cramera_wymiar_6.pickle
generator_zadan/generatory/gotowe/uklad_Cramera_wymiar_7.pickle
generator_zadan/generatory/gotowe/wyznacznik_parametr_wymiar_3.pickle
generator_zadan/generatory/gotowe/wyznacznik_parametr_wymiar_4.pickle
generator_zadan/generatory/granice.py
generator_zadan/generatory/macierze.py
generator_zadan/generatory/monotonicznosc.py
generator_zadan/generatory/szeregi_Fouriera.py
generator_zadan/generatory/uklady_rownan_liniowych.py
generator_zadan/generatory/zespolone.py
generator_zadan/wygenerowane/Chłodnictwo i Klimatyzacja--Matematyka 1-Semestr 1 - Zadania powtórzeniowe.tex
generator_zadan/wygenerowane/Informatyka--Algebra liniowa-Semestr 1 - Zadania powtórzeniowe na pierwszy termin.tex
generator_zadan/wygenerowane/Informatyka--Algebra liniowa-Semestr 1 - Zadania powtórzeniowe na poprawkę.tex
generator_zadan-0.2.11.dist-info/LICENSE
generator_zadan-0.2.11.dist-info/LICENSE.md~
generator_zadan-0.2.11.dist-info/LICENSE~
generator_zadan-0.2.11.dist-info/METADATA
generator_zadan-0.2.11.dist-info/WHEEL
generator_zadan-0.2.11.dist-info/RECORD
