Metadata-Version: 2.1
Name: generator_zadan
Version: 0.2.11
Summary: Generuje losowo roznego typu zadania
License: MIT
Author: Adam Bohonos
Requires-Python: ==3.11.*
Classifier: License :: OSI Approved :: MIT License
Classifier: Programming Language :: Python :: 3
Classifier: Programming Language :: Python :: 3.11
Requires-Dist: babel (>=2.16.0,<3.0.0)
Requires-Dist: jupyter (>=1.0.0,<2.0.0)
Requires-Dist: matplotlib (<=3.7)
Requires-Dist: notebook (>=7.4.2,<8.0.0)
Requires-Dist: numpy (>=1.26.1,<2.0.0)
Requires-Dist: pandas (>=2.1.1,<3.0.0)
Requires-Dist: pdf2image (>=1.17.0,<2.0.0)
Requires-Dist: scipy (>=1.11.3,<2.0.0)
Requires-Dist: sympy (>=1.12,<2.0)
Requires-Dist: sympy-plot-backends (>=3.0.1,<4.0.0)
Requires-Dist: tqdm (>=4.65.0,<5.0.0)
